simplebayes/categories.py
simplebayes/__init__.py
simplebayes/category.py
simplebayes-1.5.8.dist-info/RECORD
simplebayes-1.5.8.dist-info/DESCRIPTION.rst
simplebayes-1.5.8.dist-info/WHEEL
simplebayes-1.5.8.dist-info/METADATA
simplebayes-1.5.8.dist-info/metadata.json
simplebayes-1.5.8.dist-info/top_level.txt
