Metadata-Version: 2.0
Name: simplebayes
Version: 1.5.8
Summary: A memory-based, optional-persistence naïve bayesian text classifier.
Home-page: https://github.com/hickeroar/simplebayes
Author: Ryan Vennell
Author-email: ryan.vennell@gmail.com
License: MIT
Platform: UNKNOWN
Classifier: Development Status :: 5 - Production/Stable
Classifier: Intended Audience :: Developers
Classifier: License :: OSI Approved :: MIT License
Classifier: Programming Language :: Python
Classifier: Programming Language :: Python :: 2
Classifier: Programming Language :: Python :: 2.7
Classifier: Programming Language :: Python :: 3
Classifier: Programming Language :: Python :: 3.4
Classifier: Topic :: Utilities
